{
    "cities": [
        {
            "id": 1,
            "cityName": "Adelaide",
            "countryID": 1,
            "countryName": "Australia"
        },
        {
            "id": 2,
            "cityName": "Brisbane",
            "countryID": 1,
            "countryName": "Australia"
        },
        {
            "id": 3,
            "cityName": "Canberra",
            "countryID": 1,
            "countryName": "Australia"
        },
        {
            "id": 4,
            "cityName": "Darwin",
            "countryID": 1,
            "countryName": "Australia"
        },
        {
            "id": 5,
            "cityName": "Hobart",
            "countryID": 1,
            "countryName": "Australia"
        },
        {
            "id": 6,
            "cityName": "Melbourne",
            "countryID": 1,
            "countryName": "Australia"
        },

        {
            "id": 7,
            "cityName": "Perth",
            "countryID": 1,
            "countryName": "Australia"
        },
        {
            "id": 8,
            "cityName": "Sydney",
            "countryID": 1,
            "countryName": "Australia"
        },
        {
            "id": 9,
            "cityName": "Auckland",
            "countryID": 2,
            "countryName": "New Zealand"
        },
        {
            "id": 10,
            "cityName": "Christchurch",
            "countryID": 2,
            "countryName": "New Zealand"
        },
        {
            "id": 11,
            "cityName": "Wellington",
            "countryID": 2,
            "countryName": "New Zealand"
        }
    ],
    "flightRoutes": [
        {
            "id": 1,
            "originCityID": 1,
            "originCityName": "Adelaide",
            "destinationCityID": 2,
            "destinationCityName": "Brisbane"
        },
        {
            "id": 2,
            "originCityID": 1,
            "originCityName": "Adelaide",
            "destinationCityID": 3,
            "destinationCityName": "Canberra"
        },
        {
            "id": 3,
            "originCityID": 1,
            "originCityName": "Adelaide",
            "destinationCityID": 4,
            "destinationCityName": "Darwin"
        },
        {
            "id": 4,
            "originCityID": 1,
            "originCityName": "Adelaide",
            "destinationCityID": 5,
            "destinationCityName": "Hobart"
        },
        {
            "id": 5,
            "originCityID": 1,
            "originCityName": "Adelaide",
            "destinationCityID": 6,
            "destinationCityName": "Melbourne"
        },
        {
            "id": 6,
            "originCityID": 1,
            "originCityName": "Adelaide",
            "destinationCityID": 7,
            "destinationCityName": "Perth"
        },
        {
            "id": 7,
            "originCityID": 1,
            "originCityName": "Adelaide",
            "destinationCityID": 8,
            "destinationCityName": "Sydney"
        },

        {
            "id": 8,
            "originCityID": 2,
            "originCityName": "Brisbane",
            "destinationCityID": 1,
            "destinationCityName": "Adelaide"
        },
        {
            "id": 9,
            "originCityID": 2,
            "originCityName": "Brisbane",
            "destinationCityID": 3,
            "destinationCityName": "Canberra"
        },
        {
            "id": 10,
            "originCityID": 2,
            "originCityName": "Brisbane",
            "destinationCityID": 4,
            "destinationCityName": "Darwin"
        },
        {
            "id": 11,
            "originCityID": 2,
            "originCityName": "Brisbane",
            "destinationCityID": 5,
            "destinationCityName": "Hobart"
        },
        {
            "id": 12,
            "originCityID": 2,
            "originCityName": "Brisbane",
            "destinationCityID": 6,
            "destinationCityName": "Melbourne"
        },
        {
            "id": 13,
            "originCityID": 2,
            "originCityName": "Brisbane",
            "destinationCityID": 7,
            "destinationCityName": "Perth"
        },
        {
            "id": 14,
            "originCityID": 2,
            "originCityName": "Brisbane",
            "destinationCityID": 8,
            "destinationCityName": "Sydney"
        },

        {
            "id": 15,
            "originCityID": 3,
            "originCityName": "Canberra",
            "destinationCityID": 1,
            "destinationCityName": "Adelaide"
        },
        {
            "id": 16,
            "originCityID": 3,
            "originCityName": "Canberra",
            "destinationCityID": 2,
            "destinationCityName": "Brisbane"
        },
        {
            "id": 17,
            "originCityID": 3,
            "originCityName": "Canberra",
            "destinationCityID": 4,
            "destinationCityName": "Darwin"
        },
        {
            "id": 18,
            "originCityID": 3,
            "originCityName": "Canberra",
            "destinationCityID": 5,
            "destinationCityName": "Hobart"
        },
        {
            "id": 19,
            "originCityID": 3,
            "originCityName": "Canberra",
            "destinationCityID": 6,
            "destinationCityName": "Melbourne"
        },
        {
            "id": 20,
            "originCityID": 3,
            "originCityName": "Canberra",
            "destinationCityID": 7,
            "destinationCityName": "Perth"
        },
        {
            "id": 21,
            "originCityID": 3,
            "originCityName": "Canberra",
            "destinationCityID": 8,
            "destinationCityName": "Sydney"
        },

        {
            "id": 22,
            "originCityID": 4,
            "originCityName": "Darwin",
            "destinationCityID": 1,
            "destinationCityName": "Adelaide"
        },
        {
            "id": 23,
            "originCityID": 4,
            "originCityName": "Darwin",
            "destinationCityID": 2,
            "destinationCityName": "Brisbane"
        },
        {
            "id": 24,
            "originCityID": 4,
            "originCityName": "Darwin",
            "destinationCityID": 3,
            "destinationCityName": "Canberra"
        },
        {
            "id": 25,
            "originCityID": 4,
            "originCityName": "Darwin",
            "destinationCityID": 5,
            "destinationCityName": "Hobart"
        },
        {
            "id": 26,
            "originCityID": 4,
            "originCityName": "Darwin",
            "destinationCityID": 6,
            "destinationCityName": "Melbourne"
        },
        {
            "id": 27,
            "originCityID": 4,
            "originCityName": "Darwin",
            "destinationCityID": 7,
            "destinationCityName": "Perth"
        },
        {
            "id": 28,
            "originCityID": 4,
            "originCityName": "Darwin",
            "destinationCityID": 8,
            "destinationCityName": "Sydney"
        },

        {
            "id": 29,
            "originCityID": 5,
            "originCityName": "Hobart",
            "destinationCityID": 1,
            "destinationCityName": "Adelaide"
        },
        {
            "id": 30,
            "originCityID": 5,
            "originCityName": "Hobart",
            "destinationCityID": 2,
            "destinationCityName": "Brisbane"
        },
        {
            "id": 31,
            "originCityID": 5,
            "originCityName": "Hobart",
            "destinationCityID": 3,
            "destinationCityName": "Canberra"
        },
        {
            "id": 32,
            "originCityID": 5,
            "originCityName": "Hobart",
            "destinationCityID": 4,
            "destinationCityName": "Darwin"
        },
        {
            "id": 33,
            "originCityID": 5,
            "originCityName": "Hobart",
            "destinationCityID": 6,
            "destinationCityName": "Melbourne"
        },
        {
            "id": 34,
            "originCityID": 5,
            "originCityName": "Hobart",
            "destinationCityID": 7,
            "destinationCityName": "Perth"
        },
        {
            "id": 35,
            "originCityID": 5,
            "originCityName": "Hobart",
            "destinationCityID": 8,
            "destinationCityName": "Sydney"
        },

        {
            "id": 36,
            "originCityID": 6,
            "originCityName": "Melbourne",
            "destinationCityID": 1,
            "destinationCityName": "Adelaide"
        },
        {
            "id": 37,
            "originCityID": 6,
            "originCityName": "Melbourne",
            "destinationCityID": 2,
            "destinationCityName": "Brisbane"
        },
        {
            "id": 38,
            "originCityID": 6,
            "originCityName": "Melbourne",
            "destinationCityID": 3,
            "destinationCityName": "Canberra"
        },
        {
            "id": 39,
            "originCityID": 6,
            "originCityName": "Melbourne",
            "destinationCityID": 4,
            "destinationCityName": "Darwin"
        },
        {
            "id": 40,
            "originCityID": 6,
            "originCityName": "Melbourne",
            "destinationCityID": 5,
            "destinationCityName": "Hobart"
        },
        {
            "id": 41,
            "originCityID": 6,
            "originCityName": "Melbourne",
            "destinationCityID": 7,
            "destinationCityName": "Perth"
        },
        {
            "id": 42,
            "originCityID": 6,
            "originCityName": "Melbourne",
            "destinationCityID": 8,
            "destinationCityName": "Sydney"
        },
        {
            "id": 43,
            "originCityID": 6,
            "originCityName": "Melbourne",
            "destinationCityID": 11,
            "destinationCityName": "Wellington"
        },

        {
            "id": 44,
            "originCityID": 7,
            "originCityName": "Perth",
            "destinationCityID": 1,
            "destinationCityName": "Adelaide"
        },
        {
            "id": 45,
            "originCityID": 7,
            "originCityName": "Perth",
            "destinationCityID": 2,
            "destinationCityName": "Brisbane"
        },
        {
            "id": 46,
            "originCityID": 7,
            "originCityName": "Perth",
            "destinationCityID": 3,
            "destinationCityName": "Canberra"
        },
        {
            "id": 47,
            "originCityID": 7,
            "originCityName": "Perth",
            "destinationCityID": 4,
            "destinationCityName": "Darwin"
        },
        {
            "id": 48,
            "originCityID": 7,
            "originCityName": "Perth",
            "destinationCityID": 5,
            "destinationCityName": "Hobart"
        },
        {
            "id": 49,
            "originCityID": 7,
            "originCityName": "Perth",
            "destinationCityID": 6,
            "destinationCityName": "Melbourne"
        },
        {
            "id": 50,
            "originCityID": 7,
            "originCityName": "Perth",
            "destinationCityID": 8,
            "destinationCityName": "Sydney"
        },

        {
            "id": 51,
            "originCityID": 8,
            "originCityName": "Sydney",
            "destinationCityID": 1,
            "destinationCityName": "Adelaide"
        },
        {
            "id": 52,
            "originCityID": 8,
            "originCityName": "Sydney",
            "destinationCityID": 2,
            "destinationCityName": "Brisbane"
        },
        {
            "id": 53,
            "originCityID": 8,
            "originCityName": "Sydney",
            "destinationCityID": 3,
            "destinationCityName": "Canberra"
        },
        {
            "id": 54,
            "originCityID": 8,
            "originCityName": "Sydney",
            "destinationCityID": 4,
            "destinationCityName": "Darwin"
        },
        {
            "id": 55,
            "originCityID": 8,
            "originCityName": "Sydney",
            "destinationCityID": 5,
            "destinationCityName": "Hobart"
        },
        {
            "id": 56,
            "originCityID": 8,
            "originCityName": "Sydney",
            "destinationCityID": 6,
            "destinationCityName": "Melbourne"
        },
        {
            "id": 57,
            "originCityID": 8,
            "originCityName": "Sydney",
            "destinationCityID": 7,
            "destinationCityName": "Perth"
        },
        {
            "id": 58,
            "originCityID": 8,
            "originCityName": "Sydney",
            "destinationCityID": 11,
            "destinationCityName": "Wellington"
        },

        {
            "id": 59,
            "originCityID": 9,
            "originCityName": "Auckland",
            "destinationCityID": 10,
            "destinationCityName": "Christchurch"
        },
        {
            "id": 60,
            "originCityID": 9,
            "originCityName": "Auckland",
            "destinationCityID": 11,
            "destinationCityName": "Wellington"
        },

        {
            "id": 61,
            "originCityID": 10,
            "originCityName": "Christchurch",
            "destinationCityID": 9,
            "destinationCityName": "Auckland"
        },
        {
            "id": 62,
            "originCityID": 10,
            "originCityName": "Christchurch",
            "destinationCityID": 11,
            "destinationCityName": "Wellington"
        },

        {
            "id": 63,
            "originCityID": 11,
            "originCityName": "Wellington",
            "destinationCityID": 9,
            "destinationCityName": "Auckland"
        },
        {
            "id": 63,
            "originCityID": 11,
            "originCityName": "Wellington",
            "destinationCityID": 10,
            "destinationCityName": "Christchurch"
        },
        {
            "id": 64,
            "originCityID": 11,
            "originCityName": "Wellington",
            "destinationCityID": 6,
            "destinationCityName": "Melbourne"
        },
        {
            "id": 65,
            "originCityID": 11,
            "originCityName": "Wellington",
            "destinationCityID": 8,
            "destinationCityName": "Sydney"
        }
    ]
}